flaskteroids/__init__.py
flaskteroids/__main__.py
flaskteroids/actions.py
flaskteroids/app.py
flaskteroids/concern.py
flaskteroids/controller.py
flaskteroids/csrf.py
flaskteroids/current.py
flaskteroids/db.py
flaskteroids/discovery.py
flaskteroids/exceptions.py
flaskteroids/fields.py
flaskteroids/flash.py
flaskteroids/form.py
flaskteroids/inflector.py
flaskteroids/mailer.py
flaskteroids/model.py
flaskteroids/rate_limit.py
flaskteroids/registry.py
flaskteroids/rules.py
flaskteroids/cache/__init__.py
flaskteroids/cache/base.py
flaskteroids/cache/factory.py
flaskteroids/cache/inmemory.py
flaskteroids/cli/artifacts.py
flaskteroids/cli/flaskteroids.py
flaskteroids/cli/db/commands.py
flaskteroids/cli/db/config.py
flaskteroids/cli/db/templates/default/alembic.ini.mako
flaskteroids/cli/db/templates/default/env.py
flaskteroids/cli/db/templates/default/script.py.mako
flaskteroids/cli/generators/cmd_parser.py
flaskteroids/cli/generators/commands.py
flaskteroids/cli/generators/fields.py
flaskteroids/cli/generators/src_modifier.py
flaskteroids/cli/generators/templates.py
flaskteroids/cli/generators/authentication/generator.py
flaskteroids/cli/generators/authentication/templates/app/controllers/passwords_controller.py.mako
flaskteroids/cli/generators/authentication/templates/app/controllers/sessions_controller.py.mako
flaskteroids/cli/generators/authentication/templates/app/controllers/concerns/authentication.py.mako
flaskteroids/cli/generators/authentication/templates/app/mailers/passwords_mailer.py.mako
flaskteroids/cli/generators/authentication/templates/app/models/session.py.mako
flaskteroids/cli/generators/authentication/templates/app/models/user.py.mako
flaskteroids/cli/generators/authentication/templates/app/views/passwords/edit.html
flaskteroids/cli/generators/authentication/templates/app/views/passwords/new.html
flaskteroids/cli/generators/authentication/templates/app/views/passwords_mailer/reset.html
flaskteroids-0.1.6.dist-info/licenses/LICENSE
flaskteroids-0.1.6.dist-info/METADATA
flaskteroids-0.1.6.dist-info/WHEEL
flaskteroids-0.1.6.dist-info/entry_points.txt
flaskteroids-0.1.6.dist-info/top_level.txt
flaskteroids-0.1.6.dist-info/RECORD
