Metadata-Version: 2.4
Name: flaskteroids
Version: 0.1.6
Summary: Flask on steroids
Author: Juan Sebastian Quintero
License: MIT License
Classifier: Programming Language :: Python :: 3
Classifier: License :: OSI Approved :: MIT License
Classifier: Operating System :: OS Independent
Classifier: Framework :: Flask
License-File: LICENSE
Requires-Dist: alembic>=1.15.1
Requires-Dist: Flask
Requires-Dist: python-dotenv>=1.0.1
Requires-Dist: sqlalchemy
Requires-Dist: celery
Dynamic: license-file
